{"title":"Comparative Analysis of Life Cycle Assessment of Biogas-powered and Coal-powered Power Plant for Optimized Environmental Operation","link":"https://www.sciencedirect.com/science/article/pii/S2405844024151869?dgcid=rss_sd_all","date":null,"content":"<p>Publication date: Available online 10 October 2024</p><p><b>Source:</b> Heliyon</p><p>Author(s): Raman Kumawat, Lata Gidwani, Kunj Bihari Rana</p>","author":"","siteTitle":"ScienceDirect Publication: Heliyon","siteHash":"f7bd7e3f1869707615b3e54fb4ebc4eb7c817c729fd5ad33a7fd4ed65328d468","entryHash":"09d2eca19ac7a15e7901bcdebda3dc992bd3cf924f10dcbca49f69ffa77b80cc","category":"Interdisciplinary"}