{"title":"Social support in older adults: Validation and norm values of a brief form of the Perceived Social Support Questionnaire (F-SozU K-6)","link":"https://journals.plos.org/plosone/article?id=10.1371/journal.pone.0299467","date":1710856800000,"content":"<p>by Anna C. Reinwarth, Julia Petersen, Manfred E. Beutel, Martin Hautzinger, Elmar Brähler</p>\r\nBackground <p>Social relations are crucial for maintaining physical and mental health across the life span. As social roles, networks and needs change with age a valid assessment of social support in older adults and age-specific norms are necessary. The present work aims to [1) assess the level of social support in individuals &gt; 60 years of the general German population, [2) evaluate the brief six-item form of the Perceived Social Support Questionnaire (F-SozU K-6) in this age group and to [3) provide age-specific norm values.</p> Methods <p>We analyze data of <i>N</i> = 706 people representative for the German population collected in 2021. To assess social support, we used the F-SozU K-6. We tested for selectivity, item difficulty, internal consistency, construct and factor validity, as well as factorial invariance. Additionally, we assessed correlations and associations with depression, loneliness, and sociodemographic factors. Furthermore, we reported norm values for respondents &gt; 60 years.</p> Results <p>Participants &gt; 60 years reported a mean level of 23.97 (<i>SD</i> = 4.82) of social support. Results of the CFA confirmed a very good model fit. Measurement invariance across sex and age was shown. Associations with ADS and LS-S supported construct validity. Multiple regression analysis showed that female sex, increasing age, having a partner, and a higher equivalized household income were associated with higher levels of social support.</p> Conclusion <p>The F-SozU K-6 is a reliable and economical tool to assess perceived social support in older adults. Norm values for individual &gt; 60 years are provided.</p>","author":"Anna C. Reinwarth","siteTitle":"PLOS ONE","siteHash":"e9ab556ceb1e4ea76e897a5fa4f394f0bb75c2c2f3d5b0f4766ff77b4a262ac1","entryHash":"3b276a061373345efec88eaec5b51d8498afbfaae71e5b9b2661ecece7eb2346","category":"Interdisciplinary"}