{"title":"Enhanced bioenergy production through dual-chamber microbial fuel cells: Utilizing citric acid factory wastewater and grape waste as substrates","link":"https://www.sciencedirect.com/science/article/pii/S0301479724027257?dgcid=rss_sd_all","date":null,"content":"<p>Publication date: November 2024</p><p><b>Source:</b> Journal of Environmental Management, Volume 370</p><p>Author(s): Mina Sarvary Korojdeh, Mojtaba Hadavifar, Noushin Birjandi, Roya Mehrkhah, Qin Li</p>","author":"","siteTitle":"ScienceDirect Publication: Journal of Environmental Management","siteHash":"91a52f824aa08501239d7c1845cbb40b1b5cbda8cd2e69aa7907bc476614212e","entryHash":"3f65d6b6abca5a0ec7bb24b88d234b7b223242499558392abb84be3c19b847b7","category":"Environment"}