{"title":"Finding Microsoft’s Next Default Font","link":"https://www.microsoft.com/en-us/microsoft-365/blog/2021/04/28/beyond-calibri-finding-microsofts-next-default-font/","date":1621981483000,"content":"\n<p>The Microsoft Design Team:</p>\n\n<blockquote>\n  <p>Calibri has been the default font for all things Microsoft since\n2007, when it stepped in to replace Times New Roman across\nMicrosoft Office. It has served us all well, but we believe it’s\ntime to evolve. To help us set a new direction, we’ve commissioned\nfive original, custom fonts to eventually replace Calibri as the\ndefault. We’re excited to share these brand-new fonts with you\ntoday and would love your input. <a href=\"https://twitter.com/Microsoft/status/1387421368581455874\">Head over to social and tell us\nyour\nfavorite</a>.</p>\n</blockquote>\n\n<p>Asking users for input on which font should be their next default is perhaps the most Microsoftian thing in recent memory.</p>\n\n<div>\n<a href=\"https://daringfireball.net/linked/2021/05/25/microsoft-default-font\"> ★ </a>\n</div>\n\n\t","author":"John Gruber","siteTitle":"Daring Fireball","siteHash":"fc569638025dadf22a867470f8215f38855cf50e975782a6c989909474292a36","entryHash":"630bb4498f4bed9dad6d2449f977e9430617a3c15479a1f0370795f219336ca7","category":"Tech"}