{"title":"MTA: MAAP Transit Apparel brings new style to your daily bike commute","link":"https://bikerumor.com/2021/11/09/mta-maap-transit-apparel-brings-new-style-to-your-daily-bike-commute/","date":1636474008000,"content":"<p>For those times you’re not out training or riding gravel, MAAP has a new clothing range to consider. Calling it their first lifestyle collection, in this case, MTA stands for MAAP Transit Apparel. Naturally, that means clothing that is designed to wear for your daily commute, but stylish enough that you won’t want to ditch</p>\n<p>The post <a href=\"https://bikerumor.com/2021/11/09/mta-maap-transit-apparel-brings-new-style-to-your-daily-bike-commute/\">MTA: MAAP Transit Apparel brings new style to your daily bike commute</a> appeared first on <a href=\"https://bikerumor.com\">Bikerumor</a>.</p>","author":"Zach Overholt","siteTitle":"Bikerumor","siteHash":"49f427af0a926f4232eb837006841d7242e153e3afbb590f32e4b104ea3e2718","entryHash":"6da565cc73c2074d8220813de4d775565fc4c3fe683cc75680b7f208f1eb44ba","category":"Cycling"}