{"title":"Differential effect of asparagine and glutamine removal on three adenocarcinoma cell lines","link":"https://www.sciencedirect.com/science/article/pii/S2405844024118208?dgcid=rss_sd_all","date":null,"content":"<p>Publication date: 15 August 2024</p><p><b>Source:</b> Heliyon, Volume 10, Issue 15</p><p>Author(s): Greta Pessino, Leonardo Lonati, Claudia Scotti, Silvia Calandra, Ornella Cazzalini, Ombretta Iaria, Andrea Previtali, Giorgio Baiocco, Paola Perucca, Anna Tricarico, Martina Vetro, Lucia Anna Stivala, Carlo Ganini, Marta Cancelliere, Massimo Zucchetti, Isabella Guardamagna, Maristella Maggi</p>","author":"","siteTitle":"ScienceDirect Publication: Heliyon","siteHash":"f7bd7e3f1869707615b3e54fb4ebc4eb7c817c729fd5ad33a7fd4ed65328d468","entryHash":"6dca679463497d1796679028ff7d27cd140d468adfcd66e6468093daec93dfff","category":"Interdisciplinary"}