{"title":"Response on root regrowth potential to soil moisture in Sedum species during winter in Særheim, Norway","link":"https://www.sciencedirect.com/science/article/pii/S2405844024121081?dgcid=rss_sd_all","date":null,"content":"<p>Publication date: 30 August 2024</p><p><b>Source:</b> Heliyon, Volume 10, Issue 16</p><p>Author(s): Peng Ji, Yuan Chan, Mingyue Lu, Ying Zhai, Hailiang Lv, Hongyi Wang, Hans Martin Hasnslin</p>","author":"","siteTitle":"ScienceDirect Publication: Heliyon","siteHash":"f7bd7e3f1869707615b3e54fb4ebc4eb7c817c729fd5ad33a7fd4ed65328d468","entryHash":"76d690e16f9a1f9c9d36275f826e5f21405c41e28fbccd9aa7d0282b52eab0ca","category":"Interdisciplinary"}