{"title":"The effect of the ageing process on the desorption of nonylphenol in black carbon-sediment systems: a kineto-mechanistic and modeling investigation","link":"http://pubs.rsc.org/en/Content/ArticleLanding/2024/EM/D3EM00446E","date":null,"content":"<div><p><img src=\"/services/images/RSCpubs.ePlatform.Service.FreeContent.ImageService.svc/ImageService/image/GA?id=D3EM00446E\" /></p></div><div><i><b>Environ. Sci.: Processes Impacts</b></i>, 2024, <b>26</b>,499-509<br /><b>DOI</b>: 10.1039/D3EM00446E, Paper</div><div>Mingyang Sun, Han Liu, Feixiang Liu, Hong Yang, Guanghuan Cheng<br />The content of NP in the desorbing fraction was nearly equivalent to that of NP in partition sites in aged FC-sediment systems, but the release risk of NP from aged RC-sediment systems would be overestimated according to this rule.<br />The content of this RSS Feed (c) The Royal Society of Chemistry</div>","author":"","siteTitle":"RSC - Environ. Sci.: Processes Impacts latest articles","siteHash":"a19294297428f308d37ea8de36189edf4009f489794a2e42897cedcee0d94bbb","entryHash":"7e2ab63f631d50a18212e717ebcaf521056fc3687c1813ad8316289edb151955","category":"Environment"}