{"title":"L.A. School District Will Mandate Vaccines for Students","link":"https://www.nytimes.com/2021/09/09/us/la-vaccine-mandate-students-schools.html","date":1631229658000,"content":"\n<p>Dana Goldstein, reporting for The New York Times:</p>\n\n<blockquote>\n  <p>Los Angeles is the first major school district in the United\nStates to mandate coronavirus vaccines for students 12 and older\nwho are attending class in person.</p>\n\n<p>With the Delta variant ripping across the country, the district’s\nBoard of Education voted, 6-0, to pass the measure on Thursday\nafternoon. The Los Angeles Unified School District is the second\nlargest in the nation, and the mandate would eventually apply to\nmore than 460,000 students, including some enrolled at independent\ncharter schools located in district buildings.</p>\n</blockquote>\n\n<p>More like this, please.</p>\n\n<div>\n<a href=\"https://daringfireball.net/linked/2021/09/09/la-school-vaccine-mandate\"> ★ </a>\n</div>\n\n\t","author":"John Gruber","siteTitle":"Daring Fireball","siteHash":"fc569638025dadf22a867470f8215f38855cf50e975782a6c989909474292a36","entryHash":"85ca3bb9a9baed2f196906748f8b138b7789a02cd4d4fa34e755b0b75c8b2f1f","category":"Tech"}