{"title":"Alleviation of cadmium-induced oxidative damage through application of zinc oxide nanoparticles and strigolactones in Solanum lycopersicum L.","link":"http://pubs.rsc.org/en/Content/ArticleLanding/2024/EN/D3EN00796K","date":null,"content":"<div><p><img src=\"/services/images/RSCpubs.ePlatform.Service.FreeContent.ImageService.svc/ImageService/image/GA?id=D3EN00796K\" /></p></div><div><i><b>Environ. Sci.: Nano</b></i>, 2024, <b>11</b>,2633-2654<br /><b>DOI</b>: 10.1039/D3EN00796K, Paper</div><div>Vaseem Raja, Karanpal Singh, Sami Ullah Qadir, Jagpreet Singh, Ki-Hyun Kim<br />In this research, zinc oxide nanoparticles (ZnO NPs) are bio-synthesized using <em>Mangifera indica</em> leaf extract and used for reduction of cadmium (Cd) stress in tomato plants.<br />The content of this RSS Feed (c) The Royal Society of Chemistry</div>","author":"","siteTitle":"RSC - Environ. Sci.: Nano latest articles","siteHash":"b369aa8f6ff6038c80a533ff169c656640ffedd7ddca66f29ae833c000aed0b3","entryHash":"94d9fe7dac30ff262b408af7989035689a9af007cc316347d1f5f93ffe90a344","category":"Environment"}