{"title":"Here’s what it takes to Everest on a bike  (8,880m in under 15 hours!)","link":"https://bikerumor.com/2021/08/03/heres-what-it-takes-to-everest-on-a-bike-8880m-in-under-15-hours/","date":1627992668000,"content":"<p>Italian Gabriele Boasso recently completed an Everesting challenge, climbing 8,800m (28,900 feet) in just under 15 hours of ride time. Here’s how he did it, what it felt like, his bike spec, and what he ate and drank during the ride… What it felt like Everesting on a bike Starting at 5am, Gabriele rode a […]</p>\n<p>The post <a href=\"https://bikerumor.com/2021/08/03/heres-what-it-takes-to-everest-on-a-bike-8880m-in-under-15-hours/\">Here’s what it takes to Everest on a bike  (8,880m in under 15 hours!)</a> appeared first on <a href=\"https://bikerumor.com\">Bikerumor</a>.</p>","author":"Tyler Benedict","siteTitle":"Bikerumor","siteHash":"49f427af0a926f4232eb837006841d7242e153e3afbb590f32e4b104ea3e2718","entryHash":"b77ec54d319a3dbaf749c8b38fa3cb5a92bacf137c53ed9fd66e2499784635a1","category":"Cycling"}