{"title":"Therapeutic synthetic and natural materials for immunoengineering","link":"http://pubs.rsc.org/en/Content/ArticleLanding/2024/CS/D3CS00805C","date":null,"content":"<div><p><img src=\"/services/images/RSCpubs.ePlatform.Service.FreeContent.ImageService.svc/ImageService/image/GA?id=D3CS00805C\" /></p></div><div><i><b>Chem. Soc. Rev.</b></i>, 2024, <b>53</b>,1789-1822<br /><b>DOI</b>: 10.1039/D3CS00805C, Review Article</div><div><img alt=\"Open Access\" src=\"http://sod-a.rsc-cdn.org/pubs.rsc-uat.org/content/NewImages/open_access_blue.png\" /> Open Access</div><div><a href=\"http://creativecommons.org/licenses/by/3.0/\" target=\"_blank\"> <img src=\"http://sod-a.rsc-cdn.org/pubs.rsc-uat.org/content/NewImages/CCBY.png\" alt=\"Creative Commons Licence\" /></a>  This article is licensed under a <a href=\"http://creativecommons.org/licenses/by/3.0/\" target=\"_blank\">Creative Commons Attribution 3.0 Unported Licence.</a></div><div>Anna Slezak, Kevin Chang, Samir Hossainy, Aslan Mansurov, Stuart J. Rowan, Jeffrey A. Hubbell, Mustafa O. Guler<br />This review discusses the balance of inflammation in immunity and biomaterials strategies to modulate immunity in cases of imbalance such as autoimmune disease, infection, and cancer. Adapted from “Balanced Energy State”, by BioRender.com (2023).<br />The content of this RSS Feed (c) The Royal Society of Chemistry</div>","author":"","siteTitle":"RSC - Chem. Soc. Rev. latest articles","siteHash":"eafd93acc537e322f2557dc1189bea547b4fafdee33cfb4f7b3f2e3a965b832e","entryHash":"da15d795a7936eda3a363cdc783cf5637a59dea8d5061aa01015e8bd07d02158","category":"Environment"}