{"title":"Adjusted versus Targeted Fortification in Extremely Low Birth Weight Preterm Infants: Fortin Study. A Randomized Clinical Trial.","link":"https://www.preprints.org/manuscript/202407.2219/v1","date":1722243040000,"content":"Fortified human milk is the first choice for preterm infants. Although individualized fortification is recommended, the optimal method for this population remains uncertain. We conducted a comparative study assessing the growth effects of adjusted (AF) and targeted fortification (TF) in extremely low birth weight (ELBW) infants. This single-center, randomized, controlled clinical trial was conducted at a tertiary neonatal unit in Spain. Eligible participants were premature infants with a birthweight","author":"","siteTitle":"Preprints.org - The Multidisciplinary Preprint Platform","siteHash":"abac34b0506002eba4392ac15186820b9b5d7a0f2e5fce3a3511408258fb1a7e","entryHash":"eb581d200cffa0b0ad20233ee0e41ca1d8ac468703bf17c7749458cdd24a50f9","category":"Interdisciplinary"}