{"title":"GoPro HERO9 might soon be controlled by your cycling computer, watch, helmet & more!","link":"https://bikerumor.com/2021/06/23/gopro-hero9-might-soon-be-controlled-by-your-cycling-computer-watch-helmet-more/","date":1624453763000,"content":"<p>GoPro has officially opened up its API to third parties, and already have some solid partners on board to give you more ways to control your HERO9 Black action camera. And they’ve pushed out new updates that (hopefully) improve on the touchscreen sensitivity and other features… OpenGoPro API lets you tinker and hack Developers can […]</p>\n<p>The post <a href=\"https://bikerumor.com/2021/06/23/gopro-hero9-might-soon-be-controlled-by-your-cycling-computer-watch-helmet-more/\">GoPro HERO9 might soon be controlled by your cycling computer, watch, helmet &amp; more!</a> appeared first on <a href=\"https://bikerumor.com\">Bikerumor</a>.</p>","author":"Tyler Benedict","siteTitle":"Bikerumor","siteHash":"49f427af0a926f4232eb837006841d7242e153e3afbb590f32e4b104ea3e2718","entryHash":"fa725d89bb49085001c5e8302cc509348ee90533eef1fa62aa2925ac7b1f4a47","category":"Cycling"}